monggregate/__init__.py
monggregate/base.py
monggregate/dollar.py
monggregate/fields.py
monggregate/pipeline.py
monggregate/utils.py
monggregate/operators/__init__.py
monggregate/operators/operator.py
monggregate/operators/accumulators/__init__.py
monggregate/operators/accumulators/accumulator.py
monggregate/operators/accumulators/avg.py
monggregate/operators/accumulators/count.py
monggregate/operators/accumulators/first.py
monggregate/operators/accumulators/last.py
monggregate/operators/accumulators/max.py
monggregate/operators/accumulators/min.py
monggregate/operators/accumulators/push.py
monggregate/operators/accumulators/sum.py
monggregate/operators/arithmetic/__init__.py
monggregate/operators/arithmetic/add.py
monggregate/operators/arithmetic/arithmetic.py
monggregate/operators/arithmetic/divide.py
monggregate/operators/arithmetic/multiply.py
monggregate/operators/arithmetic/pow.py
monggregate/operators/arithmetic/subtract.py
monggregate/operators/array/__init__.py
monggregate/operators/array/array.py
monggregate/operators/array/array_to_object.py
monggregate/operators/array/filter.py
monggregate/operators/array/first.py
monggregate/operators/array/in_.py
monggregate/operators/array/is_array.py
monggregate/operators/array/last.py
monggregate/operators/array/max_n.py
monggregate/operators/array/min_n.py
monggregate/operators/array/size.py
monggregate/operators/array/sort_array.py
monggregate/operators/boolean/__init__.py
monggregate/operators/boolean/and_.py
monggregate/operators/boolean/boolean.py
monggregate/operators/boolean/not_.py
monggregate/operators/boolean/or_.py
monggregate/operators/comparison/__init__.py
monggregate/operators/comparison/cmp.py
monggregate/operators/comparison/comparator.py
monggregate/operators/comparison/eq.py
monggregate/operators/comparison/gt.py
monggregate/operators/comparison/gte.py
monggregate/operators/comparison/lt.py
monggregate/operators/comparison/lte.py
monggregate/operators/comparison/ne.py
monggregate-0.22.1.dist-info/METADATA
monggregate-0.22.1.dist-info/WHEEL
monggregate-0.22.1.dist-info/licenses/LICENSE
monggregate-0.22.1.dist-info/RECORD
