Metadata-Version: 2.4
Name: monggregate
Version: 0.22.1
Summary: MongoDB aggregation pipelines made easy. Joins, grouping, counting and much more...
Project-URL: Homepage, https://github.com/VianneyMI/monggregate
Project-URL: documentation, https://vianneymi.github.io/monggregate/
Author-email: Vianney Mixtur <vianney.mixtur@outlook.fr>
License: The MIT License (MIT)
License-File: LICENSE
Classifier: Development Status :: 4 - Beta
Classifier: Intended Audience :: Developers
Classifier: License :: OSI Approved :: MIT License
Classifier: Operating System :: OS Independent
Classifier: Programming Language :: Python
Classifier: Programming Language :: Python :: 3
Requires-Python: >=3.10
Requires-Dist: pydantic>=2.6.0
Requires-Dist: pyhumps>=3.0
Requires-Dist: typing-extensions>=4.0
Provides-Extra: mongodb
Requires-Dist: motor>=3.0.0; extra == 'mongodb'
Requires-Dist: pymongo>=3.0.0; extra == 'mongodb'
